sima/ROI.py
sima/__init__.py
sima/extract.py
sima/imaging.py
sima/imaging_parameters.py
sima/sequence.py
sima/spikes.py
sima/misc/__init__.py
sima/misc/align.py
sima/misc/convert.py
sima/misc/imagej.py
sima/misc/tifffile.py
sima/motion/__init__.py
sima/motion/_motion.pyd
sima/motion/dftreg.py
sima/motion/frame_align.py
sima/motion/hmm.py
sima/motion/motion.py
sima/motion/transform.py
sima/motion/tests/test_dftreg.py
sima/motion/tests/test_frame_align.py
sima/motion/tests/test_hmm.py
sima/motion/tests/test_motion.py
sima/segment/__init__.py
sima/segment/_opca.pyd
sima/segment/ca1pc.py
sima/segment/normcut.py
sima/segment/oPCA.py
sima/segment/segment.py
sima/segment/stica.py
sima/segment/tests/test_normcut.py
sima/segment/tests/test_oPCA.py
sima/segment/tests/test_segment.py
sima/tests/test_ROI.py
sima/tests/test_extract.py
sima/tests/test_imaging.py
sima/tests/test_sequence.py
sima/tests/test_spikes.py
sima/tests/data/example-volume.h5
sima/tests/data/example.h5
sima/tests/data/example.tif
sima/tests/data/imageJ_ROIs.zip
sima/tests/data/example-tiffs/0.tif
sima/tests/data/example-tiffs/1.tif
sima/tests/data/example-tiffs/2.tif
sima/tests/data/example.sima/dataset.pkl
sima/tests/data/example.sima/displacements.pkl
sima-1.3.2.dist-info/DESCRIPTION.rst
sima-1.3.2.dist-info/METADATA
sima-1.3.2.dist-info/RECORD
sima-1.3.2.dist-info/WHEEL
sima-1.3.2.dist-info/metadata.json
sima-1.3.2.dist-info/top_level.txt
