Metadata-Version: 2.0
Name: sima
Version: 1.3.2
Summary: Software for analysis of sequential imaging data
Home-page: http://www.losonczylab.org/sima/
Author: The SIMA Development Team
Author-email: software@losonczylab.org
License: GNU GPLv2
Keywords: imaging microscopy neuroscience segmentation
Platform: Linux
Platform: Mac OS-X
Platform: Windows
Classifier: Development Status :: 4 - Beta
Classifier: Intended Audience :: Science/Research
Classifier: License :: OSI Approved :: GNU General Public License v2 or later (GPLv2+)
Classifier: Operating System :: MacOS
Classifier: Operating System :: Microsoft :: Windows
Classifier: Operating System :: POSIX
Classifier: Operating System :: Unix
Classifier: Programming Language :: Python
Classifier: Topic :: Scientific/Engineering
Requires-Dist: future (>=0.14)
Requires-Dist: numpy (>=1.8)
Requires-Dist: pillow (>=2.6.1)
Requires-Dist: scikit-image (>=0.9.3)
Requires-Dist: scikit-learn (>=0.11)
Requires-Dist: scipy (>=0.13.0)
Requires-Dist: shapely (>=1.2.14)
